[
  {"slug": "complete-guide-commercial-drone-inspections-charlotte", "title": "Complete Guide to Commercial Drone Inspections in Charlotte", "category": "drone-inspections"},
  {"slug": "drone-facade-inspection-commercial-buildings", "title": "Drone Facade Inspection: How It Works for Commercial Buildings", "category": "drone-inspections"},
  {"slug": "drone-inspection-insurance-claims-guide", "title": "Drone Inspection for Insurance Claims: A Property Owner's Guide", "category": "drone-inspections"},
  {"slug": "parking-garage-drone-inspection", "title": "Parking Garage Drone Inspection: Why Traditional Methods Fall Short", "category": "drone-inspections"},
  {"slug": "thermal-imaging-commercial-roofs-drone", "title": "Thermal Imaging for Commercial Roofs: What Drone Scans Reveal", "category": "drone-inspections"},
  {"slug": "drone-roof-inspection-cost-2026", "title": "How Much Does a Drone Roof Inspection Cost? (2026 Pricing)", "category": "drone-inspections"},
  {"slug": "how-to-read-commercial-construction-estimate", "title": "How to Read a Commercial Construction Estimate Like a Pro", "category": "commercial-construction"},
  {"slug": "what-is-commercial-general-contractor", "title": "What Is a Commercial General Contractor?", "category": "commercial-construction"},
  {"slug": "commercial-construction-permits-charlotte-process", "title": "Commercial Construction Permits in Charlotte NC: Complete Process", "category": "commercial-construction"},
  {"slug": "top-10-commercial-construction-mistakes-charlotte", "title": "Top 10 Commercial Construction Mistakes Charlotte Business Owners Make", "category": "commercial-construction"},
  {"slug": "cold-storage-warehouse-construction-requirements", "title": "Cold Storage Warehouse Construction: Requirements and Costs", "category": "commercial-construction"},
  {"slug": "loading-dock-design-construction-commercial", "title": "Loading Dock Design and Construction for Commercial Warehouses", "category": "commercial-construction"},
  {"slug": "industrial-park-development-charlotte-i77-i85", "title": "Industrial Park Development Charlotte NC: I-77 and I-85 Corridor", "category": "commercial-construction"}
]
